<?xml version="1.0" encoding="UTF-8" ?>
<!DOCTYPE mapper PUBLIC "-//mybatis.org//DTD Mapper 3.0//EN" "http://mybatis.org/dtd/mybatis-3-mapper.dtd" >
<mapper namespace="com.laiketui.common.mapper.OrderModelMapper">

    <sql id="selectDynamicSQL">
        <trim prefixOverrides="and">
            <if test="store_id != null and store_id != ''">and a.store_id = #{store_id}</if>
            <if test="sNo != null and sNo != ''">and a.sNo = #{sNo}</if>
            <choose>
                <when test="recycle != null">and a.recycle=#{recycle}</when>
                <otherwise>and a.recycle != 1</otherwise>
            </choose>
            <if test="status !=null">
                <choose>
                    <when test="status.toString() == 'notClose'">and a.status <![CDATA[ <> ]]> 7</when>
                    <otherwise>and a.status = #{status}</otherwise>
                </choose>
            </if>
            <if test="startDate!=null">and a.add_time <![CDATA[  >=  ]]> #{startDate}</if>
            <if test="endDate!=null">and a.add_time <![CDATA[  <=  ]]> #{endDate}</if>
            <if test="userId!=null">and a.user_id=#{userId}</if>
            <if test="self_lifting!=null">and a.self_lifting=#{self_lifting}</if>
            <if test="otype!=null">and a.otype=#{otype}</if>
            <if test="p_sNo != null">and a.p_sNo=#{p_sNo}</if>
            <if test="mch_id!=null">and a.mch_id=concat(',',#{mch_id},',')</if>
            <if test="settlement_status != null">and a.settlement_status=#{settlement_status}</if>
            <if test="toDayOrder!=null">and DATE_FORMAT(a.add_time,'%Y-%m-%d') = #{toDayOrder}</if>
            <if test="statusList != null">
                <foreach collection="statusList" item="status" separator="," open="and status in(" close=")">
                    #{status,jdbcType=INTEGER}
                </foreach>
            </if>
            <if test=" orderTypeList != null ">
                <foreach collection="orderTypeList" item="type" separator="," open="and a.otype in(" close=")">
                    #{type}
                </foreach>
            </if>
            <if test=" orderTypeList_not != null ">
                <foreach collection="orderTypeList_not" item="type" separator="," open="and a.otype not in(" close=")">
                    #{type}
                </foreach>
            </if>
            <if test="orderType!=null and orderType != '' ">
                <choose>
                    <when test="orderType == 'payment'">and a.status = 0</when>
                    <when test="orderType == 'send'">and a.status = 1</when>
                    <when test="orderType == 'receipt'">and a.status = 2</when>
                    <when test="orderType == 'evaluete'">and a.status = 5</when>
                    <when test="orderType == 'return'">and a.sNo in (
                        select distinct r_sNo from lkt_order_details where store_id = #{storeId} and user_id = #{userId}
                        and re_type > 0 )
                    </when>
                </choose>
            </if>
            <if test="notZero!= null">and a.z_price > 0</if>
            <if test='user_recycle!= null'> and a.user_recycle = #{user_recycle} </if>
            <if test='no_comment!= null'> AND not EXISTS(select x.id from lkt_comments x where x.store_id=a.store_id and x.oid=a.sno) </if>
        </trim>
    </sql>

    <select id="selectDynamic" parameterType="Map" resultType="Map">
        select * from lkt_order a
        <where>
            <include refid="selectDynamicSQL"/>
        </where>
        <trim prefix="order by" suffixOverrides=",">
            <if test="status_sort!=null and status_sort!=''">status ${status_sort},</if>
            <if test="add_time_sort!=null and add_time_sort!=''">a.add_time ${add_time_sort},</if>
        </trim>
        <if test="pageStart != null and pageEnd != ''">limit #{pageStart},#{pageEnd}</if>
    </select>

    <select id="countDynamic" parameterType="Map" resultType="int">
        select count(1) from lkt_order a
        <where>
            <include refid="selectDynamicSQL"/>
        </where>
    </select>

    <sql id="sumMchTurnoverReportSQL">
        b.recycle = 0 and b.status = 0 and a.status in (1,2,5,7) and a.z_price > 0
        <if test="startDate!=null">and a.add_time <![CDATA[  >  ]]> #{startDate}</if>
        <if test="startEnd!=null">and a.add_time <![CDATA[  <  ]]> #{startEnd}</if>
        <if test="mchName!=null">and b.name like concat('%',#{mchName},'%')</if>
        <if test="addTimeStartBetween!=null and addTimeEndBetween">and a.add_time between #{addTimeStartBetween} and
            #{addTimeEndBetween}
        </if>
    </sql>
    <select id="sumMchTurnoverReport" parameterType="Map" resultType="Map">
        select sum(a.z_price) as total,b.name,b.id mchId from lkt_order as a left join lkt_customer as b on a.store_id =
        b.id
        <where>
            <trim prefixOverrides="and">
                <include refid="sumMchTurnoverReportSQL"/>
            </trim>
        </where>
        <trim prefix="group by" suffixOverrides=",">
            <if test="group_store_id!=null">mchId,</if>
        </trim>
        <trim prefix="order by" suffixOverrides=",">
            <if test="total_sort!=null and total_sort!=''">total ${total_sort},</if>
        </trim>
        <if test="startPage != null and pageEnd != ''">limit #{startPage},#{pageEnd}</if>
    </select>
    <select id="countMchTurnoverReport" parameterType="Map" resultType="int">
        select count(distinct a.store_id) from lkt_order as a left join lkt_customer as b on a.store_id = b.id
        <where>
            <trim prefixOverrides="and">
                <include refid="sumMchTurnoverReportSQL"/>
            </trim>
        </where>
    </select>
    <select id="sumMchTurnoverOrderReport" parameterType="Map" resultType="Map">
        select a.store_id,count(a.id) as total,b.name from lkt_order as a left join lkt_customer as b on a.store_id =
        b.id
        <where>
            <trim prefixOverrides="and">
                <include refid="sumMchTurnoverReportSQL"/>
            </trim>
        </where>
        <trim prefix="group by" suffixOverrides=",">
            <if test="group_store_id!=null">a.store_id,</if>
        </trim>
        <trim prefix="order by" suffixOverrides=",">
            <if test="total_sort!=null and total_sort!=''">total ${total_sort},</if>
        </trim>
        <if test="startPage != null and pageEnd != ''">limit #{startPage},#{pageEnd}</if>
    </select>
    <select id="countMchTurnoverOrderReport" parameterType="Map" resultType="int">
        select count(distinct a.store_id) from lkt_order as a left join lkt_customer as b on a.store_id = b.id
        <where>
            <trim prefixOverrides="and">
                <include refid="sumMchTurnoverReportSQL"/>
            </trim>
        </where>
    </select>


    <sql id="getOrdersNumDynamicSQL">
        and a.store_id = #{store_id}
        <if test="recycle != null">and a.recycle != #{recycle}</if>
        <if test="recycle1 != null">and a.recycle = #{recycle1}</if>
        <if test="id != null">and a.id = #{id}</if>
        <if test="user_id != null">and a.user_id = #{user_id}</if>
        <if test="likeOrderno != null and likeOrderno!=''">and a.sNo like CONCAT('%',#{likeOrderno},'%')</if>
        <if test="orderno != null ">and a.sNo = #{orderno}</if>
        <if test="orderType != null ">and a.otype = #{orderType}</if>
        <if test="orderStauts != null ">and a.status = #{orderStauts}</if>
        <if test="mch_id != null and mch_id!=''">and d.mch_id = #{mch_id}</if>
        <if test="supplierMchId != null">
            and p.mch_id = #{supplierMchId}
        </if>
        <if test="mch_pro != null and mch_pro!=''">AND p.mch_id = #{mch_id}</if>
        <if test="order_mch_id != null and order_mch_id!=''">and a.mch_id = concat(',',#{order_mch_id},',')</if>
        <if test="platform_activities_id != null">and a.platform_activities_id =platform_activities_id</if>
        <if test="startDay != null">and a.add_time <![CDATA[  >=  ]]> #{startDay}</if>
        <if test="endDay != null ">and a.add_time <![CDATA[  <=  ]]> #{endDay}</if>
        <if test="notOtype != null">and a.otype != #{notOtype}</if>
        <if test="statusType == 1">and a.`status` != 7</if>
        <if test="notStatusType !=null">and a.`status` != #{notStatusType}</if>
        <if test="orderFailureTime !=null and sysDate !=null">and date_add(a.add_time, interval IFNULL(order_failure_time, #{orderFailureTime})
            second) <![CDATA[  <  ]]> #{sysDate}
        </if>
        <if test="statusType == 2">and a.status = 1 and a.self_lifting = 0 </if>
        <if test="statusType == 3">and a.status = 1 and (a.self_lifting = 0 or a.self_lifting = 2) </if>
        <if test="statusType == 8">and a.status = 8  </if>
        <if test="extraction_code != null">and BINARY a.extraction_code like CONCAT(#{extraction_code},',%')</if>
        <if test="extraction_code1 != null">and a.extraction_code = #{extraction_code1}</if>
        <if test="coupon_id != null">and a.coupon_id like CONCAT('%,',#{coupon_id},',%')</if>
        <if test="recycleList != null">
            <foreach collection="recycleList" item="status" separator="," open="and a.recycle in(" close=")">
                #{status,jdbcType=INTEGER}
            </foreach>
        </if>
        <if test="statusList != null">
            <foreach collection="statusList" item="status" separator="," open="and a.status in(" close=")">
                #{status,jdbcType=INTEGER}
            </foreach>
        </if>
        <if test="orderTypeList != null">
            <foreach collection="orderTypeList" item="orderType" separator="," open="and a.otype in(" close=")">
                #{orderType}
            </foreach>
        </if>
        <if test="supplierPro == null">and p.supplier_superior is null</if>
        <if test="isSupplierPro != null">and p.supplier_superior is not null</if>
        <if test="GMSupplierPro != null">and p.supplier_superior is null</if>
        <if test="mchRecycle != null and mchRecycle != ''">and a.mch_recycle = #{mchRecycle}</if>
        <if test="pid != null and pid != ''">and p.id = #{pid}</if>
    </sql>

    <sql id="column">
        a
        .
        `id`
        ,
            a.`store_id`,
            a.`user_id`,
            a.`name`,
            a.`mobile`,
            a.`num`,
            a.`old_total`,
            a.`z_price`,
            a.`sNo`,
            a.`sheng`,
            a.`shi`,
            a.`xian`,
            a.`address`,
            a.`remark`,
            a.`pay`,
            a.`add_time`,
            a.`pay_time`,
            a.`arrive_time`,
            a.`order_failure_time`,
            a.`status`,
            a.`coupon_id`,
            a.`subtraction_id`,
            a.`consumer_money`,
            a.`coupon_activity_name`,
            a.`drawid`,
            a.`otype`,
            a.`ptcode`,
            a.`pid`,
            a.`ptstatus`,
            a.`groupman`,
            a.`refundsNo`,
            a.`trade_no`,
            a.`is_anonymous`,
            a.`logistics_service`,
            a.`overall_evaluation`,
            a.`spz_price`,
            a.`reduce_price`,
            a.`coupon_price`,
            a.`red_packet`,
            a.`allow`,
            a.`parameter`,
            a.`source`,
            a.`delivery_status`,
            a.`readd`,
            a.`remind`,
            a.`offset_balance`,
            a.`mch_id`,
            a.`zhekou`,
            a.`grade_rate`,
            a.`vip_source`,
            a.`score_deduction`,
            a.`grade_score`,
            a.`grade_fan`,
            a.`p_sNo`,
            a.`bargain_id`,
            a.`comm_discount`,
            a.`real_sno`,
            a.`orderId`,
            a.`baiduId`,
            a.`remarks`,
            a.`self_lifting`,
            a.`extraction_code`,
            a.`extraction_code_img`,
            a.`VerifiedBy_type`,
            a.`VerifiedBy`,
            a.`is_put`,
            a.`old_freight`,
            a.`z_freight`,
            a.`manual_offer`,
            a.`preferential_amount`,
            a.`recycle`,
            a.`single_store`,
            a.`pick_up_store`,
            a.`store_write_time`,
            a.`platform_activities_id`,
            a.`commission_type`,
            a.`settlement_status`,
            a.`operation_type`,
            a.`is_lssued`,
            a.`user_recycle`,
            a.`mch_recycle`,
            a.`store_recycle`,
            a.`transaction_id`,
            a.`wx_order_status`,
            a.`dividend_status`,
            a.`cancel_method`,
            a.`paypal_id`,
            a.`currency_symbol`,
            a.`exchange_rate`,
            a.`currency_code`,
            a.`stripe_id`
    </sql>


    <select id="getOrdersNumDynamic" parameterType="Map" resultType="Map">
        SELECT
        <include refid="column"/>
        ,
        a.dId,
        a.write_off_num,
        a.platform_coupon_price,
        a.store_self_delivery,
        a.store_coupon_price,
        a.p_price,
        a.mchId,
        a.after_write_off_num,
        a.mch_store_write_id,
        a.write_time,
        a.p_id,
        a.supplier_superior,
        a.p_mch_id,
        a.write_off_settings,
        a.is_appointment,
        a.write_off_mch_ids,
        a.anchor_name,
        a.live_img,
        a.currency_symbol,
        a.exchange_rate,
        a.currency_code,
        a.Dafter_discount
        FROM
        (
        SELECT
        a.*,
        row_number () over ( PARTITION BY a.sNo ) AS top,
        d.id AS dId,
        d.write_off_num,
        d.platform_coupon_price,
        d.store_self_delivery,
        d.store_coupon_price,
        d.p_price,
        d.mch_id AS mchId,
        d.after_write_off_num,
        d.mch_store_write_id,
        d.write_time,
        p.id AS p_id,
        p.supplier_superior,
        p.mch_id AS p_mch_id,
        p.write_off_settings AS write_off_settings,
        p.is_appointment,
        p.write_off_mch_ids,
        u.user_name AS anchor_name,
        u.headimgurl AS live_img,
        d.after_discount AS Dafter_discount
        FROM
        lkt_order a
        RIGHT JOIN lkt_order_details d ON a.sNo = d.r_sNo
        LEFT JOIN lkt_product_list AS p ON p.id = d.p_id
        LEFT JOIN lkt_user u ON u.user_id = d.anchor_id
        LEFT JOIN lkt_living_room r ON r.id = d.living_room_id
        <where>
            <trim prefixOverrides="and">
                <include refid="getOrdersNumDynamicSQL"/>
            </trim>
        </where>
        order by add_time desc
        ) as a
        <where>
            <if test="group_sNo!=null and group_sNo!=''">and a.top &lt;2</if>
        </where>
        <if test="pageNo!=null and pageSize!=null">
            limit #{pageNo},#{pageSize}
        </if>
    </select>
    <select id="countOrdersNumDynamic" parameterType="Map" resultType="int">
        select count( distinct a.sNo)  from lkt_order a RIGHT JOIN lkt_order_details d ON a.sNo = d.r_sNo LEFT JOIN lkt_product_list as p on p.id = d.p_id
        <where>
            <trim prefixOverrides="and">
                <include refid="getOrdersNumDynamicSQL"/>
            </trim>
        </where>
    </select>

    <select id="getOrderInfoListDynamce" parameterType="Map" resultType="Map">
        SELECT
        a.p_sNo,
        a.coupon_price,
        a.coupon_id,
        a.otype,
        b.id,
        b.r_sNo,
        b.user_id,
        b.p_id,
        b.p_name,
        b.p_price,
        b.num,
        b.r_status,
        b.sid,
        b.size,
        c.imgurl,
        a.otype,
        a.ptcode,
        c.product_class,
        d.brand_name,
        e.costprice,
        e.price
        FROM
        lkt_order a
        left join lkt_order_details b on a.sno = b.r_sNo
        left join lkt_product_list c on b.p_id=c.id
        left join lkt_brand_class d on d.brand_id = c.brand_id
        left join lkt_configure e on b.sid=e.id
        where a.store_id = #{store_id}
        <if test="sNo != null">
            and a.sNo = #{sNo}
        </if>
        <if test="status != null">
            and a.status = #{status}
        </if>
    </select>

    <select id="getOrderInfoLeftDetailDynamic" parameterType="Map" resultType="Map">
        select a.sNo, a.z_price, a.allow, a.status, a.pay, a.consumer_money, a.extraction_code,
        a.extraction_code_img, a.mch_id, b.id detailId, b.express_id, b.after_discount, b.freight,a.self_lifting,
        b.p_id, b.num, b.p_price,
        b.sid,a.add_time,b.arrive_time,b.supplier_settlement,p.gongyingshang,a.otype,a.currency_code,a.currency_symbol,a.exchange_rate
        from lkt_order as a
        left join lkt_order_details as b on a.sNo = b.r_sNo
        left join lkt_product_list p on b.p_id = p.id
        where a.store_id = #{store_id}
        <choose>
            <when test="recycle != null">and a.recycle=#{recycle}</when>
            <otherwise>and a.recycle != 1</otherwise>
        </choose>
        <if test="id != null">and a.id = #{id}</if>
        <if test="detailId != null">and b.id = #{detailId}</if>
        <if test="mch_id != null">and a.mch_id like CONCAT('%,',#{mch_id},',%')</if>
        <if test="extraction_code != null">and a.extraction_code like CONCAT('%',#{extraction_code},'%')</if>
        <if test="r_status != null">and b.r_status = #{r_status}</if>
        <if test="settlement_type != null">and b.settlement_type = #{settlement_type}</if>
        <if test="orderType != null">and a.otype = #{orderType}</if>
    </select>

    <update id="updateByOrdernoDynamic" parameterType="Map">
        update lkt_order
        <set>
            <trim suffixOverrides=",">
                <if test="status!=null">
                    status=#{status},
                </if>
                <if test="recycle != null ">
                    recycle = #{recycle},
                </if>
                <if test="name != null ">
                    name = #{name},
                </if>
                <if test="mobile != null ">
                    mobile = #{mobile},
                </if>
                <if test="address != null ">
                    address = #{address},
                </if>
                <!--                <if test="z_price != null ">-->
                <!--                    z_price = #{z_price},-->
                <!--                </if>-->
                <if test="sheng != null ">
                    sheng = #{sheng},
                </if>
                <if test="shi != null ">
                    shi = #{shi},
                </if>
                <if test="xian != null ">
                    xian = #{xian},
                </if>
                <if test="remarks != null ">
                    remarks = #{remarks},
                </if>
                <if test="recycle != null ">
                    recycle = #{recycle},
                </if>
                <if test="readd!=null">
                    readd = #{readd},
                </if>
                <if test="VerifiedBy_type!=null">
                    VerifiedBy_type = #{VerifiedBy_type},
                </if>
                <if test="VerifiedBy!=null">
                    VerifiedBy = #{VerifiedBy},
                </if>
                <if test="arrive_time!=null">
                    arrive_time = #{arrive_time},
                </if>
                <if test="cancel_method != null">
                    cancel_method = #{cancel_method},
                </if>
            </trim>
        </set>
        <where>
            <trim suffixOverrides="and">
                <if test="storeId!=null">
                    and store_id = #{storeId}
                </if>
                <if test="orderno!=null">
                    and sNo = #{orderno}
                </if>
                <if test="user_id!=null">
                    and user_id = #{user_id}
                </if>
                <if test="statusType!=null">
                    and status = #{statusType}
                </if>
                <if test="statusList!=null">
                    <foreach collection="statusList" item="status" separator="," open="and status in(" close=")">
                        #{status,jdbcType=INTEGER}
                    </foreach>
                </if>
                <if test="ordernoList!=null">
                    <foreach collection="ordernoList" item="sNo" separator="," open="and sNo in(" close=")">
                        #{sNo}
                    </foreach>
                </if>
            </trim>
        </where>
    </update>

    <!-- 个人中心 通过订单状态获取订单数量 -->
    <select id="getUserCenterOrderNumByStatus" parameterType="Map" resultType="int">
        select count(1) from lkt_order as o where o.store_id = #{storeId} and o.status = #{status} and o.recycle = 0 and
        o.user_id =#{userId}
        <if test="status == 5">
            and not EXISTS ( select c.id from lkt_comments as c where c.oid = o.sNo )
        </if>
    </select>

    <sql id="getUserCenterOrderListSQL">
        <if test="status !=null">
            <choose>
                <when test="status == 'notClose'">and a.status <![CDATA[ <> ]]> 7</when>
                <otherwise>and a.status = #{status}</otherwise>
            </choose>
        </if>
        <if test="userId!=null">and a.user_id=#{userId}</if>
        <if test="oTypeNotIn!=null">and a.otype != #{oTypeNotIn}</if>
        <if test="mchId!=null">and a.mch_id=#{mchId}</if>
        <if test="mch_id != null and mch_id != ''">and a.mch_id like CONCAT('%,',#{mch_id},',%')</if>
        <if test="otype!=null">and a.otype=#{otype}</if>
        <if test="otypeList!=null">
            <foreach collection="otypeList" item="type" separator="," open="and a.otype in(" close=")">
                #{type}
            </foreach>
        </if>
        <if test=" keyWord != '' and keyWord != null ">
            and (a.sNo like '%${keyWord}%' or d.p_name like '%${keyWord}%' or a.real_sno like '%${keyWord}%' )
        </if>
        <if test="statusNotList!=null">
            <foreach collection="statusNotList" item="status" separator="," open="and a.status not in(" close=")">
                #{status,jdbcType=INTEGER}
            </foreach>
        </if>
        <if test="orderType!=null and orderType != '' ">
            <choose>
                <when test="orderType == 'payment'">and a.status = 0  </when>
                <when test="orderType == 'send'">and a.status = 1</when>
                <when test="orderType == 'receipt'">and a.status = 2</when>
                <when test="orderType == 'write'">and a.status = 8</when>
                <when test="orderType == 'evaluete'">and a.status = 5 and not EXISTS (select x.id from lkt_comments x
                    where x.oid = a.sno and d.id=x.order_detail_id )
                </when>
                <!--                <when test="orderType == 'return'">and a.sNo in (-->
                <!--                    select r_sNo from lkt_order_details where store_id = #{storeId} and user_id = #{userId}-->
                <!--                    and re_type > 0 )-->
                <!--                </when>-->
                <when test="orderType == 'return'">and a.sNo in (
                    select sNo from lkt_return_order where store_id = #{storeId} and user_id = #{userId}
                    and re_type > 0 )
                </when>
            </choose>
        </if>
        <if test="supplierId != null">and p.gongyingshang = #{supplierId} and a.is_lssued = 1</if>
        <if test="settlement_status != null">and a.settlement_status = #{settlement_status}</if>
        <if test="orderno!=null">and a.sNo like concat('%',#{orderno},'%')</if>
        <if test="preSellCondition != null">and (a.sNo = #{preSellCondition} or p.product_title like concat('%',#{preSellCondition},'%'))</if>
        <if test="userRecycle != null and userRecycle != ''">and a.user_recycle = #{userRecycle}</if>
    </sql>
    <!-- 个人中心获取订单列表信息 -->
    <select id="getUserCenterOrderList" parameterType="Map" resultType="Map">
        SELECT
        a.allow,
        a.id,
        a.real_sno,
        a.num,
        a.vip_source,
        a.currency_code,
        a.currency_symbol,
        a.exchange_rate,
        a.z_price,
        a.sNo,
        a.add_time,
        a.status,
        a.delivery_status,
        a.otype,
        a.mch_id,
        a.sid,
        a.offset_balance,
        a.pay_time,
        a.pay_type,
        a.is_distribution,
        a.self_lifting,
        a.store_id,
        a.spz_price,
        a.single_store,
        a.settlement_status,
        a.arrive_time,
        a.z_freight,
        a.imgurl,
        a.old_total,
        a.old_freight,
        a.recycle,
        a.user_id,
        a.p_name,
        a.product_title,
        a.did,
        a.is_lssued,
        a.user_recycle,
        a.gongyingshang,
        a.wx_order_status,
        a.write_off_settings,
        a.goodsNum,
        a.voucher,
        a.review_status,
        a.reason_for_rejection
        FROM
        (
        SELECT
        a.allow,
        a.voucher,
        a.id,
        a.real_sno,
        a.num,
        a.vip_source,
        a.currency_code,
        a.currency_symbol,
        a.exchange_rate,
        a.z_price,
        a.sNo,
        row_number () over ( PARTITION BY a.sNo ) AS top,
        a.add_time,
        a.STATUS,
        a.delivery_status,
        a.otype,
        a.mch_id,
        d.sid,
        a.offset_balance,
        a.pay_time,
        a.pay AS pay_type,
        p.is_distribution,
        a.self_lifting,
        a.store_id,
        a.spz_price,
        a.single_store,
        a.settlement_status,
        a.arrive_time,
        a.z_freight,
        p.imgurl,
        a.old_total,
        a.old_freight,
        a.recycle,
        a.user_id,
        d.p_name,
        p.product_title,
        d.id as did,
        a.is_lssued,
        a.user_recycle,
        p.gongyingshang,
        a.wx_order_status,
        p.write_off_settings,
        d.num AS goodsNum,
        a.review_status,
        a.reason_for_rejection
        FROM
        lkt_order a
        RIGHT JOIN lkt_order_details d ON a.sNo = d.r_sNo
        LEFT JOIN lkt_product_list AS p ON p.id = d.p_id
        <where>
            a.store_id = #{storeId} and a.recycle = 0
            <include refid="getUserCenterOrderListSQL"/>
        </where>
        order by add_time desc
        ) AS a
        WHERE a.top &lt; 2
        <if test="start != null">
            <choose>
                <when test="pageSize!=null">limit #{start},#{pageSize}</when>
                <otherwise>LIMIT #{start},10</otherwise>
            </choose>
        </if>
    </select>

    <!-- 个人中心订单数量 -->
    <select id="getUserCenterOrderListCount" parameterType="Map" resultType="int">
        SELECT count(distinct a.sNo)
        FROM lkt_order a
        RIGHT JOIN lkt_order_details d ON a.sNo = d.r_sNo
        LEFT JOIN lkt_product_list as p on p.id = d.p_id
        <where>
            a.store_id = #{storeId} and a.recycle = 0
            <include refid="getUserCenterOrderListSQL"></include>
        </where>
    </select>

    <select id="selectOrdersReportDynamic" parameterType="Map" resultType="Map">
        SELECT
        DATE_FORMAT(a.add_time, '%Y-%m-%d') AS r_date,
        COUNT(*) AS num,
        SUM(a.z_price) AS z_price,
        COUNT(CASE WHEN a.`status` IN (1, 2, 5, 7) THEN 1 END) AS yx_num,
        SUM(CASE WHEN a.`status` IN (1, 2, 5, 7) THEN a.z_price ELSE 0 END) AS yx_amt
        FROM lkt_order a
        WHERE a.store_id = 1
        AND a.recycle = 0
        <if test="statusList_not != null">
            <foreach collection="statusList_not" item="status" separator="," open="and a.status not in(" close=")">
                #{status,jdbcType=INTEGER}
            </foreach>
        </if>
        <if test="priceGt != null">and a.z_price > #{priceGt}</if>
        <if test="statusList != null">
            <foreach collection="statusList" item="status" separator="," open="and a.status in(" close=")">
                #{status,jdbcType=INTEGER}
            </foreach>
        </if>
        <if test="startDate != null and startDate != ''">and a.add_time <![CDATA[ >= ]]> #{startDate}</if>
        <if test="endDate != null and endDate != ''">and a.add_time <![CDATA[ <= ]]> #{endDate}</if>
        GROUP BY r_date
        <if test="limit != null">
            LIMIT #{limit}
        </if>
        <if test="groupbyDate != null and groupbyDate != ''">
            group by r_date
        </if>
    </select>

    <!-- 更新订单 -->
    <update id="updateOrderInfo" parameterType="map">
        update lkt_order
        <set>
            <trim suffixOverrides=",">
                <if test="status!=null">
                    status=#{status},
                </if>
                <if test="cancleOrder != null">
                    coupon_id = 0,
                </if>
                <if test="settlement_status != null">
                    settlement_status = #{settlement_status},
                </if>
                <if test="settlement_time != null">
                    arrive_time = #{settlement_time},
                </if>
                <if test="cancel_method != null">
                    cancel_method = #{cancel_method},
                </if>
            </trim>
        </set>
        <where>
            <trim suffixOverrides="and">
                <if test="storeId!=null">
                    and store_id = #{storeId}
                </if>
                <if test="orderno!=null">
                    and sNo = #{orderno}
                </if>

                <if test="userId!=null">
                    and user_id = #{userId}
                </if>

                <if test="id!=null">
                    and id = #{id}
                </if>
            </trim>
        </where>
    </update>

    <update id="wallectPayUpdateOrder" parameterType="map">
        update lkt_order
        <set>
            <trim suffixOverrides=",">
                <!--                <if test=" zPrice != null">-->
                <!--                    z_price = offset_balance + #{zPrice},-->
                <!--                </if>-->
                <if test="status != null">
                    status = #{status},
                </if>
                <if test="pay != null">
                    pay = #{pay} ,
                </if>
                <if test="payTime != null">
                    pay_time = #{payTime} ,
                </if>
                <if test="tradeNo != null">
                    trade_no = #{tradeNo} ,
                </if>
            </trim>
        </set>
        <where>
            <trim suffixOverrides="and">
                <if test="storeId!=null">
                    and store_id = #{storeId}
                </if>
                <if test="orderno!=null">
                    and sNo = #{orderno}
                </if>
                <if test="sNo!=null">
                    and sNo = #{sNo}
                </if>
                <if test="userId!=null">
                    and user_id = #{userId}
                </if>
            </trim>
        </where>
    </update>

    <select id="getAdminOrderCount" parameterType="Map" resultType="int">
        select COUNT(distinct o.id) as num from lkt_order as o
        left join lkt_user as lu on o.user_id = lu.user_id
        right join lkt_order_details as d on o.sNo = d.r_sNo
        right join lkt_product_list as p on p.id = d.p_id
        right join lkt_mch as m on p.mch_id = m.id
        <where>
            <trim prefixOverrides="and">
                <include refid="adminOrderListSQL"/>
            </trim>
        </where>
    </select>

    <sql id="adminOrderListSQL">
        <if test=" store_id != null and store_id !=0">o.store_id = #{store_id} and lu.store_id = #{store_id}</if>
        <if test="isReturn == 'return'">and o.sNo in (
            <!-- 子查询获取每个sNo的最新退款记录，并筛选状态 -->
            select sNo from lkt_return_order ro
            where id in (
            select max(id) from lkt_return_order
            where store_id = #{store_id}
            and re_type > 0
            group by sNo  <!-- 按订单号分组，获取每组最新记录 -->
            )
            <if test="reType != null">and ro.re_type = #{reType}</if>
            <if test="rType != null">
                <choose>
                    <when test="rType == 1">
                        and ro.r_type in (1, 3) and ro.re_type = 1
                    </when>
                    <when test="rType == 2">
                        and ro.r_type in (4, 9, 13, 15)
                    </when>
                    <when test="rType == 3">
                        and ro.r_type in (2, 5, 8) and ro.re_type != 3
                    </when>
                    <when test="rType == 4">
                        and ro.r_type in (1, 3, 11) and ro.re_type = 3
                    </when>
                    <when test="rType == 5">
                        and ro.r_type = 12
                    </when>
                    <when test="rType == 6">
                        and ro.r_type in (5, 10) and ro.re_type = 3
                    </when>
                    <when test="rType == 7">
                        and ro.r_type = 0
                    </when>
                </choose>
            </if>
            )
        </if>
        <choose>
            <when test="recycle != null">and o.recycle=#{recycle}</when>
            <otherwise>and o.recycle != 1</otherwise>
        </choose>
        <if test=" recycleList != null ">
            <foreach collection="recycleList" item="recycle" separator="," open="and o.recycle in(" close=")">
                #{recycle,jdbcType=INTEGER}
            </foreach>
        </if>
        <if test="mch_recycle != null">
            and o.mch_recycle = #{mch_recycle}
        </if>
        <if test=" orderId != null ">and o.id = #{orderId}</if>
        <if test=" orderType != null ">and o.otype = #{orderType}</if>
        <if test=" orderTypeList != null ">
            <foreach collection="orderTypeList" item="type" separator="," open="and o.otype in(" close=")">
                #{type}
            </foreach>
        </if>
        <if test=" orderTypeList_not != null ">
            <foreach collection="orderTypeList_not" item="type" separator="," open="and o.otype not in(" close=")">
                #{type}
            </foreach>
        </if>
        <if test=" self_lifting != null ">and o.self_lifting = #{self_lifting}</if>
        <if test=" selfLiftingList != null ">
            <foreach collection="selfLiftingList" item="type" separator="," open="and o.self_lifting in(" close=")">
                #{type}
            </foreach>
        </if>
        <if test=" selfLiftingNotInList != null ">
            <foreach collection="selfLiftingNotInList" item="type" separator="," open="and o.self_lifting not in(" close=")">
                #{type}
            </foreach>
        </if>
        <if test=" operation_type != null ">and o.operation_type = #{operation_type}</if>
        <if test=" settlement_status != null ">and o.settlement_status = #{settlement_status}</if>
        <if test=" settlement_status_not != null ">and o.settlement_status != #{settlement_status_not}</if>
        <if test="orderno!=null">and o.sNo like concat('%',#{orderno},'%')</if>
        <if test="orderNo1!=null">and o.sNo like concat('%',#{orderNo1},'%')</if>
        <if test=" brand != null ">and lpl.brand_id = #{brand}</if>
        <if test="mch_name!=null">and m.name like concat('%',#{mch_name},'%')</if>
        <if test="mchSupplierName!=null">and (m.name like concat('%',#{mchSupplierName},'%') or s.supplier_name like concat('%',#{mchSupplierName},'%'))</if>
        <if test="source!=null">and o.source = #{source}</if>
        <if test="xOrder!=null">and (o.status = 0 or o.status = 1)</if>
        <if test="startdate!=null and startdate!='' ">and o.add_time <![CDATA[  >=  ]]> #{startdate}</if>
        <if test="enddate!=null and startdate!='' ">and o.add_time <![CDATA[  <=  ]]> #{enddate}</if>
        <if test="pay_time!=null and pay_time!='' ">and o.pay_time is not null</if>
        <if test="settlement_StartDate!=null">and o.arrive_time <![CDATA[  >=  ]]> #{settlement_StartDate}</if>
        <if test="settlement_EndDate!=null">and o.arrive_time <![CDATA[  <=  ]]> #{settlement_EndDate}</if>
        <if test="search!=null">and (o.sNo like concat('%',#{search},'%') or o.id = #{search} )</if>
        <if test="sNo!=null">and (o.sNo like concat('%',#{sNo},'%') escape '/' or lu.user_name like concat('%',#{sNo},'%') escape '/' or
            o.mobile like concat('%',#{sNo},'%') escape '/' or o.user_id like concat('%',#{sNo},'%') escape '/' or o.p_sno like
            concat('%',#{sNo},'%') escape '/' or o.name like concat('%',#{sNo},'%') escape '/' or o.real_sno like concat('%',#{sNo},'%') escape '/')
        </if>
        <if test="mchId!=null">and o.mch_id = concat(',',#{mchId},',')</if>
        <if test="groupStatus!=null">and exists(select x.id from lkt_group_open x inner join lkt_group_open_record y on x.id=y.open_id where y.sno=o.sno and x.status=#{groupStatus} )</if>
        <if test="groupStatusList!=null">
            and exists(select x.id from lkt_group_open x inner join lkt_group_open_record y on x.id=y.open_id
            where y.sno=o.sno
            <foreach collection="groupStatusList" item="type" separator="," open="and x.status in(" close=")">
                #{type}
            </foreach>
            )
        </if>
        <if test="mch_pro != null and mch_pro!=''">and o.mch_id like CONCAT('%,',#{mch_pro},',%')</if>
        <if test="mch_Id != null and mch_Id!=''">and m.id =#{mch_Id}</if>
        <!--  提现发货 -->
        <if test="deliveryStatus!=null"> and o.delivery_status = #{deliveryStatus} </if>
        <if test=" newsStatus=='0'  ">and o.status in (0,1)</if>
        <if test=" newsStatus=='1'  ">and o.status = 1</if>
        <if test="readd!=null">and o.readd = #{readd}</if>
        <if test="status !=null">and o.status = #{status}</if>
        <if test="statusList != null ">
            <foreach collection="statusList" item="status" separator="," open="and o.status in(" close=")">
                #{status,jdbcType=INTEGER}
            </foreach>
        </if>
        <choose>
            <when test=" otype == 't2' ">
                and o.otype = 'pt'
                <choose>
                    <when test="status == 'g0'">and o.status= 0</when>
                    <when test="status == 'g1'">and o.status= 9</when>
                    <when test="status == 'g2'">and o.status &gt; 0 and o.status &lt; 9</when>
                    <when test="status == 'g3'">and o.status &gt; 9</when>
                </choose>
            </when>
            <when test=" otype == 't3' ">and o.otype = 'KJ'</when>
            <when test=" otype == 't4' ">and o.otype = 'JP'</when>
            <when test=" otype == 't5' ">and o.otype = 'FX'</when>
            <when test=" otype == 't7' ">and o.otype = 'integral'</when>
            <when test=" otype == 't8' ">and o.otype = 'MS'</when>
            <when test=" otype == 'ti' ">and (o.otype = '' or o.otype = 'GM')</when>
        </choose>
        <if test="ostatus!=null">and o.status=#{ostatus}
        <if test="noStatus!=null">and o.status !=#{noStatus}</if></if>
        <if test="supplierId != null">and p.gongyingshang = #{supplierId} and o.is_lssued = 1</if>
        <if test="supplierOrder != null">and p.gongyingshang is not null and p.gongyingshang != ''</if>
        <if test="supplierOrder == null">and (p.gongyingshang is null or p.gongyingshang = '')</if>
        <if test="eliminateContainSupplier != null">AND o.sNo not in (SELECT x.r_sNo FROM lkt_order_details x RIGHT JOIN
            lkt_product_list xx ON x.p_id = xx.id AND xx.supplier_superior IS NOT NULL WHERE x.r_status = 0)
        </if>
        <if test="orderStatus != '' and orderStatus != null"> and o.pay != '' and  o.pay is not null</if>
        <if test="noPay != '' and noPay != null"> and  o.pay_time is not null</if>
        <if test="storeRecycle != null and storeRecycle != ''">and o.store_recycle = #{storeRecycle}</if>
        <if test="mchRecycle != null and mchRecycle != ''">and o.mch_recycle = #{mchRecycle}</if>
        <if test="mchStoreId != null and mchStoreId != ''"> and o.single_store = #{mchStoreId}</if>
        <if test="mchAdminId != null and mchAdminId != ''"> and  o.VerifiedBy_type = 2 and o.VerifiedBy = #{mchAdminId}</if>
        <if test="mchAdminId2 != null and mchAdminId2 != ''"> and (o.status = 2 or (o.status = 5 and o.VerifiedBy_type = 2 and o.VerifiedBy = #{mchAdminId2}))</if>
    </sql>
    <!-- 后台订单管理界面 -->
    <select id="adminOrderList" parameterType="Map" resultType="Map">
        SELECT
        a.detailId,
        a.p_id,
        a.sid,
        a.real_sno,
        a.id,
        a.consumer_money,
        a.num,
        a.sNo,
        a.name,
        a.sheng,
        a.shi,
        a.xian,
        a.source,
        a.address,
        a.add_time,
        a.mobile,
        a.old_total,
        a.old_freight,
        a.z_price,
        a.z_freight,
        a.goodsNum,
        a.pay_time,
        a.status,
        a.reduce_price,
        a.coupon_price,
        a.preferential_amount,
        a.allow,
        a.otype,
        a.ptstatus,
        a.spz_price,
        a.drawid,
        a.user_name,
        a.user_id,
        a.mch_id,
        a.num ,
        a.p_sNo,
        a.shop_id,
        a.shopName,
        a.arrive_time,
        a.settlement_status,
        a.operation_type,
        a.product_title,
        a.attribute,
        a.img,
        a.needNum,
        a.self_lifting,
        a.is_lssued,
        a.express_id,
        a.courier_num,
        a.freight,
        a.goodsAmt,
        a.after_discount,
        a.store_self_delivery,
        a.pay,
        a.supplierName,
        a.supplier_settlement,
        a.gongyingshang,
        a.supplier_superior,
        a.write_off_settings,
        a.is_appointment,
        a.commodity_type,
        a. goodsPrice,
        a.r_status,
        a.liveCommission,
        a.mchId,
        a.currency_symbol,
        a.exchange_rate,
        a.currency_code,
        a.p_integral,
        a.review_status,
        a.review_time,
        a.reason_for_rejection,
        a.voucher,
        a.cpc,
        a.shop_cpc
        FROM
        (
        SELECT
        d.id detailId,
        d.p_integral,
        d.p_id,
        d.sid,
        o.real_sno,
        o.id,
        o.consumer_money,
        o.num,
        o.sNo,
        o.name,
        o.sheng,
        o.shi,
        o.xian,
        o.source,
        o.address,
        o.add_time,
        o.mobile,
        o.old_total,
        o.old_freight,
        o.z_price,
        o.z_freight,
        count( d.id ) over(partition by o.sNo) goodsNum,
        o.pay_time,
        o.STATUS,
        o.reduce_price,
        o.coupon_price,
        o.preferential_amount,
        o.allow,
        o.otype,
        o.ptstatus,
        o.spz_price,
        o.drawid,
        lu.user_name,
        o.user_id,
        o.mch_id,
        <if test="mch_pro != '' and mch_pro != null">sum(case when d.mch_id = #{mch_pro} then 1 else 0 end)
            over(partition by o.sNo) as d_num ,
        </if>
        o.p_sNo,
        m.id AS shop_id,
        m.name shopName,
        o.arrive_time,
        o.settlement_status,
        o.operation_type,
        d.p_name product_title,
        attr.attribute,
        attr.img,
        d.num needNum,
        o.self_lifting,
        o.is_lssued,
        d.express_id,
        d.courier_num,
        d.freight,
        attr.price goodsAmt,
        d.after_discount,
        d.store_self_delivery,
        o.pay,
        s.supplier_name supplierName,
        sum( d.supplier_settlement ) over(partition by o.sNo) supplier_settlement,
        p.gongyingshang,
        p.supplier_superior,
        p.write_off_settings,
        p.is_appointment,
        p.commodity_type,
        d.p_price goodsPrice,
        d.r_status,
        d.commission AS liveCommission,
        d.mch_id AS mchId,
        o.currency_symbol,
        o.exchange_rate,
        o.currency_code,
        ROW_NUMBER() over(partition by o.sNo) AS top,
        ROW_NUMBER() over(partition by d.id) AS top2,
        o.review_status,
        o.review_time,
        o.reason_for_rejection,
        o.voucher,
        o.cpc,
        o.shop_cpc
        FROM
        lkt_order AS o
        LEFT JOIN lkt_user AS lu ON o.user_id = lu.user_id
        RIGHT JOIN lkt_order_details AS d ON o.sNo = d.r_sNo
        RIGHT JOIN lkt_configure attr ON attr.id = d.sid
        RIGHT JOIN lkt_product_list AS p ON p.id = attr.pid
        RIGHT JOIN lkt_mch AS m ON p.mch_id = m.id
        LEFT JOIN lkt_payment pay ON pay.class_name = o.pay
        LEFT JOIN lkt_supplier AS s ON p.gongyingshang = s.id
        <where>
            <trim prefixOverrides="and">
                <include refid="adminOrderListSQL"/>
            </trim>
        </where>
        <trim prefix="order by" suffixOverrides=",">
            <if test="diy_status_sort!=null and diy_status_sort!=''">FIELD(o.`status`, 1, 0, 2,5,7)
                ${diy_status_sort},
            </if>
            <if test="order_status_sort!=null and order_status_sort!=''">
                FIELD(o.`status`, ${order_status_sort}) ASC ,
            </if>
            <if test="add_time_sort!=null and add_time_sort!=''">o.add_time ${add_time_sort},</if>
        </trim>
        ) AS a
        <where>
            <if test="group_sNo!=null and group_sNo!=''">and a.top &lt;2</if>
            <if test="group_detail_id!=null and group_detail_id!=''">and a.top2 &lt;2</if>
        </where>
        <!-- 外层新增排序逻辑：基于 add_time_sort 对结果最终排序 -->
        <trim prefix="order by" suffixOverrides=",">
            <if test="add_time_sort!=null and add_time_sort!=''">
                a.add_time ${add_time_sort},  <!-- 注意使用外层别名 a -->
            </if>
        </trim>
        <if test="start != null and pagesize != ''">limit #{start},#{pagesize}</if>
    </select>

    <select id="countAdminOrderList" parameterType="Map" resultType="int">
        select count(distinct o.sNo)
        from lkt_order as o
        left join lkt_user as lu on o.user_id = lu.user_id
        right join lkt_order_details as d on o.sNo = d.r_sNo
        RIGHT JOIN lkt_configure attr on attr.id=d.sid
        right join lkt_product_list as p on p.id = attr.pid
        right join lkt_mch as m on p.mch_id = m.id
        left join lkt_supplier as s on p.gongyingshang = s.id
        <where>
            <trim prefixOverrides="and">
                <include refid="adminOrderListSQL"/>
            </trim>
        </where>
    </select>

    <select id="getOrderAllPrice" parameterType="Map" resultType="BigDecimal">
        select IFNULL(SUM(z_price), 0)
        from lkt_order as o
        left join lkt_user as lu on o.user_id = lu.user_id
        right join lkt_order_details as d on o.sNo = d.r_sNo
        RIGHT JOIN lkt_configure attr on attr.id=d.sid
        right join lkt_product_list as p on p.id = attr.pid
        right join lkt_mch as m on p.mch_id = m.id
        <where>
            <trim prefixOverrides="and">
                <include refid="adminOrderListSQL"/>
            </trim>
        </where>
    </select>


    <!-- 后台订单列表商品信息 -->
    <select id="adminOrderListProductInfo" resultType="Map" parameterType="Map">
        select lpl.imgurl,lpl.product_title,lpl.product_number,lod.p_price,lod.unit,lod.num,lod.size,
        lod.p_id,lod.courier_num,lod.express_id,lod.freight,lpl.brand_id ,lm.name as mchname,lod.r_status
        from lkt_order_details as lod
        left join lkt_product_list as lpl on lpl.id=lod.p_id
        LEFT JOIN lkt_mch as lm on lm.id = lpl.mch_id
        where r_sNo= #{sNo}
        <if test=" brand != null ">
            and lpl.brand_id = #{brand}
        </if>
    </select>

    <!-- 获取订单发货信息列表 -->
    <select id="getDeleiveryOrders" resultType="Map" parameterType="Map">
        select o.p_sNo,
               o.otype,
               o.mch_id,
               d.id,
               d.r_sNo,
               d.user_id,
               d.p_id,
               d.p_name,
               d.p_price,
               d.num,
               d.r_status,
               d.sid,
               d.size,
               p.imgurl,
               o.otype,
               o.currency_symbol,
               o.exchange_rate,
               o.currency_code,
               o.self_lifting,
               d.supplier_settlement,
               d.deliver_num,
               b.brand_name
        from lkt_order_details as d
                 left join lkt_configure as attr on attr.id = d.sid
                 left join lkt_product_list as p on p.id = attr.pid
                 left join lkt_order as o on d.r_sNo = o.sNo
                 left join lkt_brand_class as b on p.brand_id = b.brand_id
        where d.store_id = #{storeId}
          and d.r_sNo = #{orderNo}
          and d.r_status = 1
          and d.deliver_num  <![CDATA[ < ]]> d.num
          and not EXISTS(
                select x.id from lkt_return_order x where x.p_id = d.id and x.r_type not in (2, 4, 5, 8, 9, 10, 12))
    </select>

    <!-- 发货时候获取订单详情  -->
    <select id="getDeliveryOrdersInfo" resultType="Map" parameterType="Map">
        select o.id,
               o.user_id,
               o.sNo,
               d.p_name,
               d.p_id,
               d.sid,
               d.num,
               o.name,
               o.currency_symbol,
               o.exchange_rate,
               o.currency_code,
               o.address
        from lkt_order as o
                 left join lkt_order_details as d on o.sNo = d.r_sNo
        where o.store_id = #{storeId}
          and d.id in (#{orderDetailsId})
    </select>


    <sql id="getOrderInfoListUserSQL">
        <if test="store_id != null">and o.store_id = #{store_id}</if>
        <if test="r_status != null">and d.r_status = #{r_status}</if>
        <if test="r_status_not != null">and d.r_status != #{r_status_not}</if>
        <if test="ptcode != null">and o.ptcode = #{ptcode}</if>
    </sql>

    <select id="getOrderInfoListUser" resultType="Map" parameterType="Map">
        SELECT u.user_name,d.p_name,c.img,d.p_id as goods_id,d.sid as attr_id,o.* ,d.size,c.price goodsPrice
        from lkt_order as o
        LEFT JOIN lkt_user as u on o.user_id = u.user_id
        LEFT JOIN lkt_order_details as d on o.sNo = d.r_sNo
        LEFT JOIN lkt_configure as c on d.sid = c.id
        <where>
            <trim prefixOverrides="and">
                <include refid="getOrderInfoListUserSQL"/>
            </trim>
        </where>
        <trim prefix="order by" suffixOverrides=",">
            <if test="add_time_sort!=null and add_time_sort!=''">o.add_time ${add_time_sort},</if>
        </trim>
        <if test="pageStart != null and pageEnd != ''">limit #{pageStart},#{pageEnd}</if>
    </select>

    <select id="countOrderInfoListUser" resultType="int" parameterType="Map">
        SELECT count(1)
        from lkt_order as o
        LEFT JOIN lkt_user as u on o.user_id = u.user_id
        LEFT JOIN lkt_order_details as d on o.sNo = d.r_sNo
        LEFT JOIN lkt_configure as c on d.sid = c.id
        <where>
            <trim prefixOverrides="and">
                <include refid="getOrderInfoListUserSQL"/>
            </trim>
        </where>
    </select>


    <sql id="selectbMchOrderIndexSQL">
        and o.status != 8 and o.recycle in (0,2)
        <if test="store_id != null">and o.store_id = #{store_id} and lu.store_id = o.store_id</if>
        <if test="source != null">and o.source = #{source}</if>
        <if test="otype != null">and o.otype = #{otype}</if>
        <if test="status != null">and o.status = #{status}</if>
        <if test="self_lifting != null">and o.self_lifting = #{self_lifting}</if>
        <if test="mch_id != null">and o.mch_id = concat(',',#{mch_id},',')</if>
        <if test="order_like != null">and (o.sNo like concat('%',#{order_like},'%') or o.name like
            concat('%',#{order_like},'%')
            or o.mobile like concat('%',#{order_like},'%') or o.user_id like concat('%',#{order_like},'%') or o.p_sNo
            like
            concat('%',#{order_like},'%')
        </if>
        <if test="startDate != null">and o.add_time <![CDATA[  >=  ]]> #{startDate}</if>
        <if test="endDate != null">and o.add_time <![CDATA[  <=  ]]> #{endDate}</if>
    </sql>
    <select id="selectbMchOrderIndex" resultType="Map" parameterType="Map">
        SELECT
        a.id,
        a.consumer_money,
        a.num,
        a.sNo,
        a.NAME,
        a.sheng,
        a.shi,
        a.xian,
        a.source,
        a.address,
        a.add_time,
        a.mobile,
        a.z_price,
        a.STATUS,
        a.reduce_price,
        a.coupon_price,
        a.allow,
        a.drawid,
        a.otype,
        a.ptcode,
        a.ptstatus,
        a.spz_price,
        a.pay,
        a.user_name,
        a.user_id,
        a.mch_id,
        a.p_sNo,
        a.coupon_id,
        a.self_lifting,
        a.arrive_time,
        a.payName,
        a.currency_symbol,
        a.exchange_rate,
        a.currency_code
        FROM
        (
        SELECT
        o.id,
        o.consumer_money,
        o.num,
        o.sNo,
        o.NAME,
        o.sheng,
        o.shi,
        o.xian,
        o.source,
        o.address,
        o.add_time,
        o.mobile,
        o.z_price,
        o.STATUS,
        o.reduce_price,
        o.coupon_price,
        o.allow,
        o.drawid,
        o.otype,
        o.ptcode,
        o.ptstatus,
        o.spz_price,
        o.pay,
        lu.user_name,
        o.user_id,
        o.mch_id,
        o.p_sNo,
        o.coupon_id,
        o.self_lifting,
        o.arrive_time,
        pay.NAME payName,
        o.currency_symbol,
        o.exchange_rate,
        o.currency_code,
        ROW_NUMBER() over(partition by o.sNo) AS top
        FROM
        lkt_order AS o
        LEFT JOIN lkt_user AS lu ON o.user_id = lu.user_id
        LEFT JOIN lkt_payment pay ON pay.class_name = o.pay
        <where>
            <trim prefixOverrides="and">
                <include refid="selectbMchOrderIndexSQL"/>
            </trim>
        </where>
        <trim prefix="order by" suffixOverrides=",">
            <if test="add_time_sort!=null and add_time_sort!=''">o.add_time ${add_time_sort},</if>
        </trim>
        ) AS a
        <where>
            <if test="group_sNo!=null and group_sNo!=''">and a.top &lt;2</if>
        </where>
        <if test="pageStart != null and pageEnd != ''">limit #{pageStart},#{pageEnd}</if>
    </select>
    <select id="countbMchOrderIndex" resultType="int" parameterType="Map">
        select count(1)
        from lkt_order as o
        left join lkt_user as lu on o.user_id = lu.user_id
        <where>
            <trim prefixOverrides="and">
                <include refid="selectbMchOrderIndexSQL"/>
            </trim>
        </where>
    </select>
    <select id="sumbMchOrderIndexByPrice" resultType="Map" parameterType="Map">
        select SUM(o.z_price) z_price,COUNT(o.id) num
        from lkt_order as o
        left join lkt_user as lu on o.user_id = lu.user_id
        <where>
            <trim prefixOverrides="and">
                <include refid="selectbMchOrderIndexSQL"/>
            </trim>
        </where>
    </select>
  <!--  <select id="getChargeMoney" resultType="java.util.Map">
        SELECT sum(a.num*a.p_price)amount,m.name from lkt_order_details a
        LEFT JOIN lkt_product_list b on a.p_id=b.id INNER JOIN lkt_mch m on b.mch_id=m.id
        <where>
            <if test="storeid!=null and  storeid!=''">
                a.store_id=#{storeid}
            </if>
            <if test="startDate!=null and  startDate!=''">
                and a.add_time <![CDATA[>= ]]>#{startDate}
            </if>
        </where>
        GROUP BY b.mch_id ORDER BY amount desc
    </select>-->
    <select id="getChargeMoney" resultType="java.util.Map">
        SELECT
        IFNULL(SUM(a.z_price), 0) AS amount,
        ANY_VALUE(m_sub.name) AS name
        FROM lkt_order a
        INNER JOIN (
        SELECT r_sNo, name, id
        FROM (
        SELECT
        d.r_sNo,
        m.name,
        m.id,
        ROW_NUMBER() OVER (PARTITION BY d.r_sNo ORDER BY d.r_sNo) AS rn
        FROM lkt_order_details d
        INNER JOIN lkt_product_list b ON d.p_id = b.id
        INNER JOIN lkt_mch m ON b.mch_id = m.id
        ) t
        WHERE rn = 1
        ) m_sub
        ON a.sNo = m_sub.r_sNo
        <if test="storeid!=null and  storeid!=''">
            and a.store_id=#{storeid}
        </if>
        <if test="startDate!=null and  startDate!=''">
            and a.add_time <![CDATA[ >= ]]>#{startDate}
        </if>
        AND a.pay_time IS NOT NULL
        AND a.settlement_status = 1
        GROUP BY a.mch_id
        ORDER BY amount DESC
        LIMIT 0, 10;
    </select>
    <select id="getSaledGoodsNum" parameterType="Map" resultType="java.lang.Long">
        select ifnull(sum(a.num), 0) from lkt_order_details a INNER JOIN lkt_product_list b on a.p_id=b.id
        <where>
            a.r_status in(1,2,5,7)
            <choose>
                <when test="index==0">
                    and b.mch_id=#{mchId}
                    and (b.gongyingshang ='' or b.gongyingshang is null)
                </when>
                <when test="index==1">
                    and b.mch_id!=#{mchId}
                    and (b.gongyingshang ='' or b.gongyingshang is null)
                </when>
                <when test="index==2">
                    and b.gongyingshang!=''
                </when>
            </choose>
            <if test="storeid!=null and  storeid!=''">
                and b.store_id=#{storeid}
            </if>
            <if test="date!=null and date!=''">
                and DATE_FORMAT( a.add_time, '%Y-%m-%d' ) <![CDATA[ <= ]]>#{date}
            </if>
        </where>
    </select>
    <select id="getOrderNumByPeriod" resultType="java.lang.Integer">
        select count(1) from lkt_order a
        RIGHT JOIN lkt_order_details c on c.r_sNo = a.sNo
        RIGHT JOIN lkt_product_list b on c.p_id=b.id
        <where>
            DATE_FORMAT(a.add_time,'%Y-%m-%d') <![CDATA[ >= ]]> #{startDate}
            and DATE_FORMAT(a.add_time,'%Y-%m-%d') <![CDATA[ <= ]]> #{endDate} and a.store_id=#{storeid} and a.recycle=0 and a.otype='GM'
            <choose>
                <when test="status==3">
                    and not exists (select * from lkt_comments c where a.id=c.oid) and a.status= 5
                </when>
                <otherwise>
                    and a.status=#{status}
                </otherwise>
            </choose>
            AND a.store_recycle = 1
            AND ( b.gongyingshang IS NULL OR b.gongyingshang = '' )
        </where>
    </select>


<!--    select (ifnull(sum(a.z_price),0 ) - (	select ifnull(sum(real_money),0) from lkt_return_order where r_type in(4,9) and store_id=1 and sNo in(-->
<!--    select sNo-->
<!--    from-->
<!--    lkt_order a-->
<!--    where-->
<!--    a.store_id=#{storeid}-->
<!--    AND-->
<!--    DATE_FORMAT(pay_time,"%Y-%m-%d")=#{date}-->
<!--    )))  total-->
<!--    from-->
<!--    lkt_order a-->
<!--    where-->
<!--    a.store_id=#{storeid}-->
<!--    AND-->
<!--    DATE_FORMAT(a.pay_time,"%Y-%m-%d")=#{date}-->
    <select id="getCurrentVolume" resultType="java.math.BigDecimal">
        SELECT
            ifnull( sum( a.z_price ), 0 )
        FROM
            lkt_order a
        WHERE
            a.store_id = #{storeid}

          AND DATE_FORMAT( a.pay_time, "%Y-%m-%d" )= #{date}
    </select>

    <select id="getCurrentVolumeByMonth" resultType="java.math.BigDecimal">
        select
            ifnull(sum(a.z_price),0 )
        from
            lkt_order a
        where
            store_id=#{storeid}
          AND
            DATE_FORMAT(pay_time,"%Y-%m")=#{date}
    </select>

    <select id="sumAllMoeny" resultType="java.math.BigDecimal">
        select (ifnull(sum(a.z_price),0 ) - (select ifnull(sum(real_money),0) from lkt_return_order where r_type in(4,9) and store_id=#{storeid} and sNo IN(SELECT sNo FROM lkt_order where store_id = #{storeid})))  total
        from
            lkt_order a
        where
            store_id=#{storeid}
    </select>
    <select id="countByUser" resultType="map">
        SELECT
            sum( z_price ) amount,
            user_id name,
            user_id
        FROM
            lkt_order a
        WHERE
            a.store_id=#{storeid}
          and  a.add_time>= #{date}
          AND status = 5
          and recycle = 0
        GROUP BY
            a.user_id
        ORDER BY
            amount DESC
            LIMIT 0,10
    </select>

    <select id="countByUser1" resultType="map">
        SELECT
            sum( z_price ) amount,
            user_id name,
            user_id
        FROM
            lkt_order a
        WHERE
            a.store_id=#{storeid}
          AND status = 5
          and recycle = 0
        GROUP BY
            a.user_id
        ORDER BY
            amount DESC
            LIMIT 0,10
    </select>
    <sql id="getMchSonOrderListSql">
        AND a.self_lifting IN (1,3)
        AND a.recycle IN ( 0, 2 )
        and (a.otype = 'GM' or a.otype = 'MS')
        <if test="store_id != null and store_id != ''">and a.store_id = #{store_id}</if>
        <if test="otype != null and otype != ''">and a.otype = #{otype}</if>
        <if test="mchId != nill and mchId != ''"> and a.mch_id LIKE  CONCAT('%', #{mchId},'%')</if>
        <if test="mch_store_id != null and mch_store_id != ''"> and a.single_store = #{mch_store_id}</if>
        <if test="key != null and key != ''"> and a.sNo like concat('%',#{key},'%')</if>
        <if test="startdate!=null and startdate!='' ">and a.add_time <![CDATA[  >=  ]]> #{startdate}</if>
        <if test="enddate!=null and startdate!='' ">and a.add_time <![CDATA[  <=  ]]> #{enddate}</if>
        <choose>
            <when test="status == 1">
                and a.status IN (2,8)
            </when>
            <when test="status == 2">
                and a.status = 5 and  a.VerifiedBy_type = 2 and a.VerifiedBy = #{administrators_id}
            </when>
        </choose>
    </sql>

    <select id="getMchSonOrderList" resultType="Map" parameterType="Map">
        select
        a.id,
        a.store_id,
        a.user_id,
        a.NAME,
        a.mobile,
        a.num,
        a.old_total,
        a.z_price,
        a.sNo,
        a.sheng,
        a.shi,
        a.xian,
        a.address,
        a.remark,
        a.pay,
        a.add_time,
        a.pay_time,
        a.status,
        a.coupon_id,
        a.subtraction_id,
        a.consumer_money,
        a.coupon_activity_name,
        a.drawid,
        a.otype,
        a.ptcode,
        a.refundsNo,
        a.trade_no,
        a.is_anonymous,
        a.spz_price,
        a.reduce_price,
        a.coupon_price,
        a.red_packet,
        a.allow,
        a.source,
        a.delivery_status,
        a.readd,
        a.remind,
        a.offset_balance,
        a.mch_id,
        a.zhekou,
        a.grade_rate,
        a.grade_fan,
        a.p_sNo,
        a.bargain_id,
        a.comm_discount,
        a.real_sno,
        a.remarks,
        a.self_lifting,
        a.extraction_code,
        a.extraction_code_img,
        a.is_put,
        a.z_freight,
        a.manual_offer,
        a.preferential_amount,
        a.recycle,
        a.single_store,
        a.pick_up_store,
        a.currency_symbol,
        a.currency_code,
        a.exchange_rate,
        a.commission_type,
        a.settlement_status,
        a.operation_type
        from lkt_order as a
        <where>
            <trim prefixOverrides="and">
                <include refid="getMchSonOrderListSql"/>
            </trim>
        </where>
        <trim prefix="order by" suffixOverrides=",">
            <if test="add_time_sort!=null and add_time_sort!=''">a.add_time ${add_time_sort},</if>
        </trim>
        <if test="page != null and page != ''">limit #{page},10</if>
    </select>

    <select id="getMchSonOrderCount" parameterType="Map" resultType="int">
        select count(1) from lkt_order a
        <where>
            <include refid="getMchSonOrderListSql"/>
        </where>
    </select>
    <select id="getMchSonOrderCountVI" resultType="Map" parameterType="Map">
        SELECT
        a.*,c.write_off_mch_ids,b.mch_store_write_id
        FROM
        lkt_order a
        LEFT JOIN lkt_order_details b on a.sNo=b.r_sNo
        LEFT JOIN lkt_product_list c on b.p_id=c.id
        <where>
            a.self_lifting =3
            AND a.recycle IN ( 0, 2 )
            <if test="store_id != null and store_id != ''">and a.store_id = #{store_id}</if>
            AND a.otype = 'VI'
            <if test="mchId != null and mchId != ''"> and a.mch_id LIKE  CONCAT('%', #{mchId},'%')</if>
            <if test="key != null and key != ''"> and a.sNo like concat('%',#{key},'%')</if>
            <choose>
                <when test="status == 1">
                    and a.status IN (8)
                </when>
                <when test="status == 2">
                    and a.status = 5 and  a.VerifiedBy_type = 2
                </when>
            </choose>
            and (c.write_off_mch_ids = '0' or c.write_off_mch_ids like concat('%',#{write_off_mch_ids},'%')  )
            and (b.mch_store_write_id IS null or b.mch_store_write_id = #{write_off_mch_ids})
        </where>
           order by  a.add_time desc ,id
        <if test="page != null and pageSize!=null">
            LIMIT #{page},#{pageSize}
        </if>
    </select>
    <select id="cleanVIWrite" resultType="java.util.Map">
        SELECT
            o.*
        FROM
            lkt_order o
            LEFT JOIN lkt_order_details d ON o.sNo = d.r_sNo
        WHERE
            d.write_time IS NOT NULL
          AND o.pay_time IS NULL
          and o.mch_id  like concat('%',#{mchId},'%')
          and o.store_id = #{storeId}
          and o.status = 0
          and o.otype='VI'
    </select>
    <select id="statistics" resultType="java.util.Map">

    </select>
    <select id="getOrderNumByDay" resultType="java.util.Map">

        SELECT
        DATE_FORMAT(add_time, '%m-%d') AS time,
        COUNT(1) AS value
        FROM `lkt_order`
        WHERE
        store_id = #{storeId}
        AND recycle = 0
        <if test='mchId != null and mchId != ""'>
            mch_id = CONCAT(',',#{mchId},',')
        </if>
        AND STATUS IN (1, 2, 5, 7)
        AND z_price > 0
        AND pay_time IS NOT NULL
        -- 修正：直接用日期函数比较，避免重复格式化
        AND add_time &gt;= STR_TO_DATE(#{startDate}, '%Y-%m-%d')
        AND add_time &lt;= DATE_ADD(STR_TO_DATE(#{endDate}, '%Y-%m-%d'), INTERVAL 1 DAY)
        GROUP BY
        DATE_FORMAT(add_time, '%Y-%m-%d'), -- 按完整日期分组（与筛选条件对应）
        DATE_FORMAT(add_time, '%m-%d') -- 确保 SELECT 中的非聚合列在 GROUP BY 中
        ORDER BY
        DATE_FORMAT(add_time, '%Y-%m-%d') -- 按日期排序，保证结果顺序
    </select>
    <select id="getSaleNumByHour" resultType="java.util.Map">
        SELECT
        CONCAT(HOUR(add_time), '时') AS time,
        IFNULL(SUM(z_price), 0) AS value
        FROM `lkt_order`
        WHERE
        store_id = #{storeId}
        AND recycle = 0
        <if test='mchId != null and mchId != ""'>
            AND mch_id = CONCAT(',',#{mchId},',')
        </if>
        AND add_time &gt;= STR_TO_DATE(#{date}, '%Y-%m-%d')
        AND add_time &lt;= DATE_ADD(STR_TO_DATE(#{date}, '%Y-%m-%d'), INTERVAL 1 DAY)
        AND STATUS IN (1, 2, 5, 7)
        AND pay_time IS NOT NULL
        GROUP BY
        HOUR(add_time)
        ORDER BY
        HOUR(add_time);
    </select>
    <select id="getSaleNumByMonth" resultType="java.util.Map">
        SELECT
        DATE_FORMAT(add_time, '%m/%d') AS time,
        IFNULL(SUM(z_price), 0) AS value
        FROM (
        SELECT
        add_time,
        z_price,
        ROW_NUMBER() OVER (
        PARTITION BY DATE_FORMAT(add_time, '%Y-%m-%d')
        ORDER BY add_time ASC -- 按任意顺序，确保每组一条记录
        ) AS rn
        FROM `lkt_order`
        WHERE
        store_id = #{storeId}
        AND recycle = 0
        <if test="mchId != null">
            mch_id = CONCAT(',',#{mchId},',')
        </if>
        AND add_time <![CDATA[  >=  ]]> #{startDate}
        AND add_time <![CDATA[  <  ]]> #{endDate}
        AND STATUS IN(1, 2,5,7) AND pay_time is not null
        ) AS t
        WHERE
        t.rn = 1
        GROUP BY
        DATE_FORMAT(t.add_time, '%Y-%m-%d'); -- 按完整日期分组
    </select>

    <select id="selectByIds" resultType="com.laiketui.domain.order.OrderModel">
        SELECT id, self_lifting
        FROM lkt_order
        WHERE id IN
        <foreach collection="ids" item="id" open="(" separator="," close=")">
            #{id}
        </foreach>
    </select>

</mapper>
